askp.py
askp_cli-1.0.8.dist-info/licenses/LICENSE
askp_cli-1.0.8.dist-info/METADATA
askp_cli-1.0.8.dist-info/WHEEL
askp_cli-1.0.8.dist-info/entry_points.txt
askp_cli-1.0.8.dist-info/top_level.txt
askp_cli-1.0.8.dist-info/RECORD
