Metadata-Version: 2.4
Name: askp-cli
Version: 1.0.8
Summary: A command-line interface for Perplexity AI
Home-page: https://github.com/liensimen/askp
Author: LienS
Author-email: Simen Lien <simen@cvcv.no>
License-Expression: MIT
Project-URL: Homepage, https://github.com/liensimen/askp
Project-URL: Bug Reports, https://github.com/liensimen/askp/issues
Project-URL: Source, https://github.com/liensimen/askp
Keywords: perplexity,ai,cli,command-line,chat,assistant
Classifier: Development Status :: 4 - Beta
Classifier: Intended Audience :: Developers
Classifier: Operating System :: OS Independent
Classifier: Programming Language :: Python :: 3
Classifier: Programming Language :: Python :: 3.8
Classifier: Programming Language :: Python :: 3.9
Classifier: Programming Language :: Python :: 3.10
Classifier: Programming Language :: Python :: 3.11
Classifier: Programming Language :: Python :: 3.12
Classifier: Topic :: Software Development :: Libraries :: Python Modules
Classifier: Topic :: Utilities
Requires-Python: >=3.8
License-File: LICENSE
Requires-Dist: requests>=2.31.0
Requires-Dist: colorama>=0.4.6
Requires-Dist: prompt_toolkit>=3.0.47
Requires-Dist: pypdf>=4.2.0
Requires-Dist: Pillow>=10.0.0
Requires-Dist: pytesseract>=0.3.10
Requires-Dist: python-docx>=0.8.11
Requires-Dist: beautifulsoup4>=4.12.0
Requires-Dist: pyperclip>=1.8.2
Dynamic: author
Dynamic: home-page
Dynamic: license-file
Dynamic: requires-python
